mksite/__about__.py
mksite/__init__.py
mksite/__main__.py
mksite/config.py
mksite/exceptions.py
mksite/parser.py
mksite/persistence.py
mksite/renderer.py
mksite/cli/__init__.py
mksite-0.1.1.dist-info/METADATA
mksite-0.1.1.dist-info/WHEEL
mksite-0.1.1.dist-info/entry_points.txt
mksite-0.1.1.dist-info/licenses/LICENSE.txt
mksite-0.1.1.dist-info/RECORD
