Metadata-Version: 2.3
Name: mksite
Version: 0.1.1
Summary: Static site generator that supports markdown and html.
Project-URL: Homepage, https://sr.ht/~loges/mksite
Project-URL: Source, https://git.sr.ht/~loges/mksite
Project-URL: Issues, https://todo.sr.ht/~loges/mksite
Author-email: Logan Connolly <me@loganconnolly.com>
License-Expression: GPL-3.0-or-later
License-File: LICENSE.txt
Classifier: Development Status :: 4 - Beta
Classifier: Programming Language :: Python
Classifier: Programming Language :: Python :: 3.11
Classifier: Programming Language :: Python :: 3.12
Classifier: Programming Language :: Python :: Implementation :: CPython
Classifier: Programming Language :: Python :: Implementation :: PyPy
Requires-Python: >=3.11
Requires-Dist: click
Requires-Dist: haitch
Requires-Dist: mistletoe
